{
  "IsModified": false,
  "IsNew": false,
  "Description": "You can command the forces of nature! Storm Summoning allows you to control wind and weather to aid your allies and wreak havoc on your foes.",
  "SetName": "Storm_Summoning",
  "FullName": "Mastermind_Buff.Storm_Summoning",
  "ImageName": "StormSummon.png",
  "Power": null,
  "SetType": "Secondary",
  "DisplayName": "Storm Summoning",
  "nArchetype": 10,
  "nID": 2722,
  "SubName": "Storm Summoning",
  "ATClass": "Class_Mastermind",
  "UIDTrunkSet": "",
  "nIDTrunkSet": 0,
  "UIDLinkSecondary": "",
  "nIDLinkSecondary": 0,
  "UIDMutexSets": [],
  "nIDMutexSets": [],
  "Group": null,
  "GroupName": "Mastermind_Buff",
  "Powers": []
}