{
  "IsModified": false,
  "IsNew": false,
  "Description": "Poison",
  "SetName": "Poison_Trap",
  "FullName": "Villain_Pets.Poison_Trap",
  "ImageName": "",
  "Power": null,
  "SetType": "Pet",
  "DisplayName": "Poison Trap",
  "nArchetype": -1,
  "nID": 3191,
  "SubName": "Poison",
  "ATClass": "",
  "UIDTrunkSet": "",
  "nIDTrunkSet": 0,
  "UIDLinkSecondary": "",
  "nIDLinkSecondary": 0,
  "UIDMutexSets": [],
  "nIDMutexSets": [],
  "Group": null,
  "GroupName": "Villain_Pets",
  "Powers": []
}