{
  "IsModified": false,
  "IsNew": false,
  "Description": "Mu Mastery",
  "SetName": "Mu_Adept",
  "FullName": "Villain_Pets.Mu_Adept",
  "ImageName": "",
  "Power": null,
  "SetType": "Pet",
  "DisplayName": "Mu Adept",
  "nArchetype": -1,
  "nID": 3181,
  "SubName": "Mu Mastery",
  "ATClass": "",
  "UIDTrunkSet": "",
  "nIDTrunkSet": 0,
  "UIDLinkSecondary": "",
  "nIDLinkSecondary": 0,
  "UIDMutexSets": [],
  "nIDMutexSets": [],
  "Group": null,
  "GroupName": "Villain_Pets",
  "Powers": []
}