{
  "IsModified": false,
  "IsNew": false,
  "Description": "Enhances the accuracy of a power by {Boost.Attrib.Accuracy.Scale}%, the range of a power by {Boost.Attrib.Range.Scale}% and reduces interrupt time by {Boost.Attrib.Interrupt.Scale}%",
  "SetName": "Attuned_Extreme_Measures_C",
  "FullName": "Boosts.Attuned_Extreme_Measures_C",
  "ImageName": "",
  "Power": null,
  "SetType": "Boost",
  "DisplayName": "Attuned Extreme Measures C",
  "nArchetype": -1,
  "nID": 317,
  "SubName": "Set: Extreme Measures",
  "ATClass": "",
  "UIDTrunkSet": "",
  "nIDTrunkSet": 0,
  "UIDLinkSecondary": "",
  "nIDLinkSecondary": 0,
  "UIDMutexSets": [],
  "nIDMutexSets": [],
  "Group": null,
  "GroupName": "Boosts",
  "Powers": []
}