{
  "IsModified": false,
  "IsNew": false,
  "Description": "Enhances the accuracy of a power by {Boost.Attrib.Accuracy.Scale}% and reduces the recharge time of a power by {Boost.Attrib.Recharge.Scale}%.",
  "SetName": "Crafted_Befuddling_Aura_A",
  "FullName": "Boosts.Crafted_Befuddling_Aura_A",
  "ImageName": "",
  "Power": null,
  "SetType": "Boost",
  "DisplayName": "Crafted Befuddling Aura A",
  "nArchetype": -1,
  "nID": 936,
  "SubName": "Set: Befuddling Aura",
  "ATClass": "",
  "UIDTrunkSet": "",
  "nIDTrunkSet": 0,
  "UIDLinkSecondary": "",
  "nIDLinkSecondary": 0,
  "UIDMutexSets": [],
  "nIDMutexSets": [],
  "Group": null,
  "GroupName": "Boosts",
  "Powers": []
}