{
  "IsModified": false,
  "IsNew": false,
  "Description": "Ghost Widow has granted you access to the power of darkness and souls. She has shown you how to use the souls of your victims to destroy your enemies. This has granted you access to powers and abilities you have never had before.",
  "SetName": "Brute_Soul_Mastery",
  "FullName": "Epic.Brute_Soul_Mastery",
  "ImageName": "PatronDrain.png",
  "Power": null,
  "SetType": "Ancillary",
  "DisplayName": "Soul Mastery",
  "nArchetype": -1,
  "nID": 2627,
  "SubName": "Soul Mastery",
  "ATClass": "",
  "UIDTrunkSet": "",
  "nIDTrunkSet": 0,
  "UIDLinkSecondary": "",
  "nIDLinkSecondary": 0,
  "UIDMutexSets": [],
  "nIDMutexSets": [],
  "Group": null,
  "GroupName": "Epic",
  "Powers": []
}