{
  "IsModified": false,
  "IsNew": false,
  "Description": "UNIQUE -- No more than 1 enhancement of this type may be slotted by a character.  Enhances the accuracy by {Boost.Attrib.Accuracy.Scale}%, the Stun duration by {Boost.Attrib.Stun.Scale}% and reduces the recharge time of a power by {Boost.Attrib.Recharge.Scale}%.",
  "SetName": "Superior_Attuned_Absolute_Amazement_C",
  "FullName": "Boosts.Superior_Attuned_Absolute_Amazement_C",
  "ImageName": "",
  "Power": null,
  "SetType": "Boost",
  "DisplayName": "Superior Attuned Absolute Amazement C",
  "nArchetype": -1,
  "nID": 2180,
  "SubName": "Set: Absolute Amazement",
  "ATClass": "",
  "UIDTrunkSet": "",
  "nIDTrunkSet": 0,
  "UIDLinkSecondary": "",
  "nIDLinkSecondary": 0,
  "UIDMutexSets": [],
  "nIDMutexSets": [],
  "Group": null,
  "GroupName": "Boosts",
  "Powers": []
}