{
  "IsModified": false,
  "IsNew": false,
  "Description": "Enhances the damage of a power by {Boost.Attrib.Damage.Scale}% and reduces recharge cost by {Boost.Attrib.Recharge.Scale}%.",
  "SetName": "Attuned_Smashing_Haymaker_C",
  "FullName": "Boosts.Attuned_Smashing_Haymaker_C",
  "ImageName": "",
  "Power": null,
  "SetType": "Boost",
  "DisplayName": "Attuned Smashing Haymaker C",
  "nArchetype": -1,
  "nID": 717,
  "SubName": "Set: Smashing Haymaker",
  "ATClass": "",
  "UIDTrunkSet": "",
  "nIDTrunkSet": 0,
  "UIDLinkSecondary": "",
  "nIDLinkSecondary": 0,
  "UIDMutexSets": [],
  "nIDMutexSets": [],
  "Group": null,
  "GroupName": "Boosts",
  "Powers": []
}