{
  "IsModified": false,
  "IsNew": false,
  "Description": "Enhances the damage of a power by {Boost.Attrib.Damage.Scale}% and reduces endurance cost by {Boost.Attrib.Endurance.Scale}%",
  "SetName": "Crafted_Volley_Fire_B",
  "FullName": "Boosts.Crafted_Volley_Fire_B",
  "ImageName": "",
  "Power": null,
  "SetType": "Boost",
  "DisplayName": "Crafted Volley Fire B",
  "nArchetype": -1,
  "nID": 1891,
  "SubName": "Set: Volley Fire",
  "ATClass": "",
  "UIDTrunkSet": "",
  "nIDTrunkSet": 0,
  "UIDLinkSecondary": "",
  "nIDLinkSecondary": 0,
  "UIDMutexSets": [],
  "nIDMutexSets": [],
  "Group": null,
  "GroupName": "Boosts",
  "Powers": []
}