{
  "IsModified": false,
  "IsNew": false,
  "Description": "Enhances the range of a power by {Boost.Attrib.Range.Scale}% and stun duration by {Boost.Attrib.Stun.Scale}%.",
  "SetName": "Attuned_Stagger_D",
  "FullName": "Boosts.Attuned_Stagger_D",
  "ImageName": "",
  "Power": null,
  "SetType": "Boost",
  "DisplayName": "Attuned Stagger D",
  "nArchetype": -1,
  "nID": 740,
  "SubName": "Set: Stagger",
  "ATClass": "",
  "UIDTrunkSet": "",
  "nIDTrunkSet": 0,
  "UIDLinkSecondary": "",
  "nIDLinkSecondary": 0,
  "UIDMutexSets": [],
  "nIDMutexSets": [],
  "Group": null,
  "GroupName": "Boosts",
  "Powers": []
}