{
  "IsModified": false,
  "IsNew": false,
  "Description": "Increases flight speed by {Boost.Attrib.FlySpeed.Scale}%.",
  "SetName": "Crafted_Fly_45",
  "FullName": "Boosts.Crafted_Fly_45",
  "ImageName": "",
  "Power": null,
  "SetType": "Boost",
  "DisplayName": "Crafted Fly 45",
  "nArchetype": -1,
  "nID": 1218,
  "SubName": "Invention",
  "ATClass": "",
  "UIDTrunkSet": "",
  "nIDTrunkSet": 0,
  "UIDLinkSecondary": "",
  "nIDLinkSecondary": 0,
  "UIDMutexSets": [],
  "nIDMutexSets": [],
  "Group": null,
  "GroupName": "Boosts",
  "Powers": []
}