{
  "IsModified": false,
  "IsNew": false,
  "Description": "Claws are bones or blades that extend from your hands and cause Lethal damage. The lightweight, natural feel of claws gives this power set a reduced Endurance cost and faster attack rate than other Stalker melee sets.  Like all Stalker primary attack powers, Claw attacks can land a Critical Hit for double damage, if you are properly Hidden or if your target is Slept or Held.",
  "SetName": "Claws_Assassins_Strike",
  "FullName": "Villain_Pets.Claws_Assassins_Strike",
  "ImageName": "",
  "Power": null,
  "SetType": "Pet",
  "DisplayName": "",
  "nArchetype": -1,
  "nID": 3133,
  "SubName": "Claws",
  "ATClass": "",
  "UIDTrunkSet": "",
  "nIDTrunkSet": 0,
  "UIDLinkSecondary": "",
  "nIDLinkSecondary": 0,
  "UIDMutexSets": [],
  "nIDMutexSets": [],
  "Group": null,
  "GroupName": "Villain_Pets",
  "Powers": []
}