{
  "IsModified": false,
  "IsNew": false,
  "Description": "Enhances the effectiveness of accuracy and defense debuffs and increases the accuracy of a power.",
  "SetName": "Hamidon_DeBuff_Accuracy",
  "FullName": "Boosts.Hamidon_DeBuff_Accuracy",
  "ImageName": "",
  "Power": null,
  "SetType": "Boost",
  "DisplayName": "Hamidon DeBuff Accuracy",
  "nArchetype": -1,
  "nID": 1938,
  "SubName": "Hamidon (All Origins)",
  "ATClass": "",
  "UIDTrunkSet": "",
  "nIDTrunkSet": 0,
  "UIDLinkSecondary": "",
  "nIDLinkSecondary": 0,
  "UIDMutexSets": [],
  "nIDMutexSets": [],
  "Group": null,
  "GroupName": "Boosts",
  "Powers": []
}