{
  "IsModified": false,
  "IsNew": false,
  "Description": "Reduces the endurance cost of a power by {Boost.Attrib.Endurance.Scale}% and recharge time by {Boost.Attrib.Recharge.Scale}%",
  "SetName": "Attuned_Aegis_C",
  "FullName": "Boosts.Attuned_Aegis_C",
  "ImageName": "",
  "Power": null,
  "SetType": "Boost",
  "DisplayName": "Attuned Aegis C",
  "nArchetype": -1,
  "nID": 36,
  "SubName": "Set: Aegis",
  "ATClass": "",
  "UIDTrunkSet": "",
  "nIDTrunkSet": 0,
  "UIDLinkSecondary": "",
  "nIDLinkSecondary": 0,
  "UIDMutexSets": [],
  "nIDMutexSets": [],
  "Group": null,
  "GroupName": "Boosts",
  "Powers": []
}