{
  "IsModified": false,
  "IsNew": false,
  "Description": "Enhances the accuracy of a power by {Boost.Attrib.Accuracy.Scale}%,  the damage by {Boost.Attrib.Damage.Scale}%, and reduces recharge time by {Boost.Attrib.Recharge.Scale}%.",
  "SetName": "Crafted_Thunderstrike_D",
  "FullName": "Boosts.Crafted_Thunderstrike_D",
  "ImageName": "",
  "Power": null,
  "SetType": "Boost",
  "DisplayName": "Crafted Thunderstrike D",
  "nArchetype": -1,
  "nID": 1802,
  "SubName": "Set: Thunderstrike",
  "ATClass": "",
  "UIDTrunkSet": "",
  "nIDTrunkSet": 0,
  "UIDLinkSecondary": "",
  "nIDLinkSecondary": 0,
  "UIDMutexSets": [],
  "nIDMutexSets": [],
  "Group": null,
  "GroupName": "Boosts",
  "Powers": []
}